brainplotlib/__init__.py
brainplotlib/data/example_data.npy
brainplotlib/data/fsaverage_to_inflated_image.npy
brainplotlib/data/fsaverage_to_midthickness_image.npy
brainplotlib/data/fsaverage_to_pial_image.npy
brainplotlib/data/fsaverage_to_white_image.npy
brainplotlib/data/mask_fsaverage5_lh.npy
brainplotlib/data/mask_fsaverage5_rh.npy
brainplotlib/data/mask_fsaverage6_lh.npy
brainplotlib/data/mask_fsaverage6_rh.npy
brainplotlib/data/mask_fsaverage_lh.npy
brainplotlib/data/mask_fsaverage_rh.npy
brainplotlib/data/voronoi_fsaverage_lh_icoorder3.npy
brainplotlib/data/voronoi_fsaverage_lh_icoorder4.npy
brainplotlib/data/voronoi_fsaverage_lh_icoorder5.npy
brainplotlib/data/voronoi_fsaverage_lh_icoorder6.npy
brainplotlib/data/voronoi_fsaverage_rh_icoorder3.npy
brainplotlib/data/voronoi_fsaverage_rh_icoorder4.npy
brainplotlib/data/voronoi_fsaverage_rh_icoorder5.npy
brainplotlib/data/voronoi_fsaverage_rh_icoorder6.npy
brainplotlib-1.0.0.dist-info/LICENSE.txt
brainplotlib-1.0.0.dist-info/METADATA
brainplotlib-1.0.0.dist-info/WHEEL
brainplotlib-1.0.0.dist-info/top_level.txt
brainplotlib-1.0.0.dist-info/RECORD
