Metadata-Version: 2.1
Name: brainplotlib
Version: 1.0.0
Summary: A lightweight package to plot brain surfaces with Python.
Home-page: https://feilong.github.io/brainplotlib/
Author: Ma Feilong
Author-email: mafeilong@gmail.com
Project-URL: Bug Tracker, https://github.com/feilong/brainplotlib/issues
Project-URL: Source Code, https://github.com/feilong/brainplotlib
Keywords: brain,surface,fmri,plotting,visualization
Classifier: Programming Language :: Python :: 3 :: Only
Classifier: Programming Language :: Python :: 3.6
Classifier: Programming Language :: Python :: 3.7
Classifier: Programming Language :: Python :: 3.8
Classifier: Programming Language :: Python :: 3.9
Classifier: Programming Language :: Python :: 3.10
Requires-Python: >=3.6
License-File: LICENSE.txt
Requires-Dist: numpy
Requires-Dist: matplotlib
Provides-Extra: tests
Requires-Dist: pytest ; extra == 'tests'
